investec_api_python/__init__.py
investec_api_python/client.py
investec_api_python/http_api_client.py
investec_api_python/sa_card_code.py
investec_api_python/sa_pb_account_information.py
investec_api_python-0.1.0.dist-info/LICENSE
investec_api_python-0.1.0.dist-info/METADATA
investec_api_python-0.1.0.dist-info/WHEEL
investec_api_python-0.1.0.dist-info/RECORD
