Metadata-Version: 2.1
Name: investec-api-python
Version: 0.1.0
Summary: Python client for Investec Programmable Banking
License: MIT
Author: Tai Lucas
Author-email: tglucas@gmail.com
Requires-Python: >=3.10,<4.0
Classifier: License :: OSI Approved :: MIT License
Classifier: Programming Language :: Python :: 3
Classifier: Programming Language :: Python :: 3.10
Classifier: Programming Language :: Python :: 3.11
Requires-Dist: requests (>=2.31.0,<3.0.0)
